[
  {
    "slug": "emergency-lockouts",
    "title": "Emergency Lockouts",
    "description": "Residential, commercial, and automotive lockout help with 24/7 response.",
    "icon": "locked-door",
    "href": "/services#emergency-lockouts",
    "offered": true
  },
  {
    "slug": "lock-rekeying",
    "title": "Lock Rekeying",
    "description": "Keep your existing hardware and change who can access the property.",
    "icon": "cylinder-key",
    "href": "/services#lock-rekeying",
    "offered": true
  },
  {
    "slug": "lock-installation",
    "title": "Lock Installation",
    "description": "Deadbolts, smart locks, and high-security cylinders installed correctly.",
    "icon": "deadbolt",
    "href": "/services#lock-installation",
    "offered": true
  },
  {
    "slug": "automotive-keys",
    "title": "Automotive Keys",
    "description": "Key duplication, fob programming, and ignition repair for everyday access issues.",
    "icon": "key-fob",
    "href": "/services#automotive-keys",
    "offered": true
  },
  {
    "slug": "commercial-security",
    "title": "Commercial Security",
    "description": "Master key systems, access control planning, and safe security support.",
    "icon": "keypad-entry",
    "href": "/services#commercial-security",
    "offered": false
  },
  {
    "slug": "security-assessments",
    "title": "Security Assessments",
    "description": "On-site reviews with practical recommendations for homes and businesses.",
    "icon": "clipboard-shield",
    "href": "/services#security-assessments",
    "offered": false
  }
]
